HttpLibrary/__init__.py
HttpLibrary/livetest.py
robotframework_newhttplibrary-1.1.6.dist-info/METADATA
robotframework_newhttplibrary-1.1.6.dist-info/WHEEL
robotframework_newhttplibrary-1.1.6.dist-info/top_level.txt
robotframework_newhttplibrary-1.1.6.dist-info/zip-safe
robotframework_newhttplibrary-1.1.6.dist-info/RECORD
